pyjxslt/XSLTGateway.py
pyjxslt/XSLTLibrary.py
pyjxslt/__init__.py
pyjxslt/xsl/XMLToJson.xsl
pyjxslt-user-defined-address/XSLTGateway.py
pyjxslt-user-defined-address/XSLTLibrary.py
pyjxslt-user-defined-address/__init__.py
pyjxslt-user-defined-address/xsl/XMLToJson.xsl
pyjxslt_user_defined_address-0.7.4.data/data/lib/pyjxslt/Saxon-HE-9.7.0-1.jar
pyjxslt_user_defined_address-0.7.4.data/data/lib/pyjxslt/py4j-0.9.jar
pyjxslt_user_defined_address-0.7.4.data/data/lib/pyjxslt/pyjxslt.jar
pyjxslt_user_defined_address-0.7.4.data/scripts/pyjxslt
pyjxslt_user_defined_address-0.7.4.data/scripts/testgateway
pyjxslt_user_defined_address-0.7.4.dist-info/METADATA
pyjxslt_user_defined_address-0.7.4.dist-info/WHEEL
pyjxslt_user_defined_address-0.7.4.dist-info/top_level.txt
pyjxslt_user_defined_address-0.7.4.dist-info/zip-safe
pyjxslt_user_defined_address-0.7.4.dist-info/RECORD
